{
  "folio": "178112",
  "folio_raw": "VE-178112",
  "fecha_proceso": "2026-06-19T14:56:39.731123",
  "fuente_descarga": "DOCUMENTOS_ANEXOS",
  "estado": "OK",
  "metadatos_satys": {
    "representante_legal": "COMUNÍCALO DE MÉXICO, S.A. DE C.V.",
    "nombre_operador": "JOSÉ LUIS CARRILLO SALAS",
    "asunto": "INFORMES ESTADISTICOS 2026",
    "tipo_tramite": "CGPE-01-008: Entrega periódica de Información General Estadística para efectos del Acervo Estadístico del Instituto Federal de Telecomunicaciones.",
    "fecha_registro": "22/05/2026",
    "solicitante": "",
    "descripcion": "",
    "folio": "178112"
  },
  "metadatos_tramite": {
    "tipo_tramite": "CGPE-01-008: Entrega periódica de Información General Estadística para efectos del Acervo Estadístico del Instituto Federal de Telecomunicaciones.",
    "fecha_registro": "22/05/2026",
    "solicitante": "",
    "nombre_operador": "JOSÉ LUIS CARRILLO SALAS",
    "representante_legal": "COMUNÍCALO DE MÉXICO, S.A. DE C.V.",
    "asunto": "INFORMES ESTADISTICOS 2026",
    "descripcion": "",
    "folio": "178112"
  },
  "total_archivos_encontrados": 12,
  "total_archivos_ok": 12,
  "total_archivos_error": 0,
  "coincide": true,
  "archivos": [
    {
      "folio": "178112",
      "archivo": "17794969812298r020-01-com_1t_2026_vf.csv",
      "nombre_original": "documento_178112_1",
      "tipo": "",
      "fecha": "",
      "descripcion": "",
      "ruta": "descargas\\178112\\17794969812298r020-01-com_1t_2026_vf.csv",
      "tamano_kb": 0.0,
      "ok": true,
      "url": "https://ventanilla.ift.org.mx/VentanillaElectronica/upload/diversos/17794969812298r020-01-com_1t_2026_vf.csv",
      "fuente": "DOCUMENTOS_ANEXOS"
    },
    {
      "folio": "178112",
      "archivo": "17794969602139r015-02-com_1t_2026_vf.csv",
      "nombre_original": "documento_178112_2",
      "tipo": "",
      "fecha": "",
      "descripcion": "",
      "ruta": "descargas\\178112\\17794969602139r015-02-com_1t_2026_vf.csv",
      "tamano_kb": 0.1,
      "ok": true,
      "url": "https://ventanilla.ift.org.mx/VentanillaElectronica/upload/diversos/17794969602139r015-02-com_1t_2026_vf.csv",
      "fuente": "DOCUMENTOS_ANEXOS"
    },
    {
      "folio": "178112",
      "archivo": "17794969436690r015-01-com_1t_2026_vf.csv",
      "nombre_original": "documento_178112_3",
      "tipo": "",
      "fecha": "",
      "descripcion": "",
      "ruta": "descargas\\178112\\17794969436690r015-01-com_1t_2026_vf.csv",
      "tamano_kb": 0.1,
      "ok": true,
      "url": "https://ventanilla.ift.org.mx/VentanillaElectronica/upload/diversos/17794969436690r015-01-com_1t_2026_vf.csv",
      "fuente": "DOCUMENTOS_ANEXOS"
    },
    {
      "folio": "178112",
      "archivo": "17794969273179r012-01-com_1t-2026_vf.csv",
      "nombre_original": "documento_178112_4",
      "tipo": "",
      "fecha": "",
      "descripcion": "",
      "ruta": "descargas\\178112\\17794969273179r012-01-com_1t-2026_vf.csv",
      "tamano_kb": 0.1,
      "ok": true,
      "url": "https://ventanilla.ift.org.mx/VentanillaElectronica/upload/diversos/17794969273179r012-01-com_1t-2026_vf.csv",
      "fuente": "DOCUMENTOS_ANEXOS"
    },
    {
      "folio": "178112",
      "archivo": "17794968993983r008-05-com_1t-2026_vf.csv",
      "nombre_original": "documento_178112_5",
      "tipo": "",
      "fecha": "",
      "descripcion": "",
      "ruta": "descargas\\178112\\17794968993983r008-05-com_1t-2026_vf.csv",
      "tamano_kb": 0.1,
      "ok": true,
      "url": "https://ventanilla.ift.org.mx/VentanillaElectronica/upload/diversos/17794968993983r008-05-com_1t-2026_vf.csv",
      "fuente": "DOCUMENTOS_ANEXOS"
    },
    {
      "folio": "178112",
      "archivo": "17794968922471r008-04-com_1t-2026_vf.csv",
      "nombre_original": "documento_178112_6",
      "tipo": "",
      "fecha": "",
      "descripcion": "",
      "ruta": "descargas\\178112\\17794968922471r008-04-com_1t-2026_vf.csv",
      "tamano_kb": 0.1,
      "ok": true,
      "url": "https://ventanilla.ift.org.mx/VentanillaElectronica/upload/diversos/17794968922471r008-04-com_1t-2026_vf.csv",
      "fuente": "DOCUMENTOS_ANEXOS"
    },
    {
      "folio": "178112",
      "archivo": "1779496884232r008-03-com_1t-2026_vf.csv",
      "nombre_original": "documento_178112_7",
      "tipo": "",
      "fecha": "",
      "descripcion": "",
      "ruta": "descargas\\178112\\1779496884232r008-03-com_1t-2026_vf.csv",
      "tamano_kb": 3.2,
      "ok": true,
      "url": "https://ventanilla.ift.org.mx/VentanillaElectronica/upload/diversos/1779496884232r008-03-com_1t-2026_vf.csv",
      "fuente": "DOCUMENTOS_ANEXOS"
    },
    {
      "folio": "178112",
      "archivo": "17794968468296r008-02-com_1t-2026_vf.csv",
      "nombre_original": "documento_178112_8",
      "tipo": "",
      "fecha": "",
      "descripcion": "",
      "ruta": "descargas\\178112\\17794968468296r008-02-com_1t-2026_vf.csv",
      "tamano_kb": 2.8,
      "ok": true,
      "url": "https://ventanilla.ift.org.mx/VentanillaElectronica/upload/diversos/17794968468296r008-02-com_1t-2026_vf.csv",
      "fuente": "DOCUMENTOS_ANEXOS"
    },
    {
      "folio": "178112",
      "archivo": "17794968252734r008-01-com_1t-2026_vf.csv",
      "nombre_original": "documento_178112_9",
      "tipo": "",
      "fecha": "",
      "descripcion": "",
      "ruta": "descargas\\178112\\17794968252734r008-01-com_1t-2026_vf.csv",
      "tamano_kb": 0.1,
      "ok": true,
      "url": "https://ventanilla.ift.org.mx/VentanillaElectronica/upload/diversos/17794968252734r008-01-com_1t-2026_vf.csv",
      "fuente": "DOCUMENTOS_ANEXOS"
    },
    {
      "folio": "178112",
      "archivo": "17794967852831r003-05-com_1t-2026_vf.csv",
      "nombre_original": "documento_178112_10",
      "tipo": "",
      "fecha": "",
      "descripcion": "",
      "ruta": "descargas\\178112\\17794967852831r003-05-com_1t-2026_vf.csv",
      "tamano_kb": 0.1,
      "ok": true,
      "url": "https://ventanilla.ift.org.mx/VentanillaElectronica/upload/diversos/17794967852831r003-05-com_1t-2026_vf.csv",
      "fuente": "DOCUMENTOS_ANEXOS"
    },
    {
      "folio": "178112",
      "archivo": "Sarccontroller",
      "nombre_original": "documento_178112_11",
      "tipo": "",
      "fecha": "",
      "descripcion": "",
      "ruta": "descargas\\178112\\Sarccontroller",
      "tamano_kb": 26.6,
      "ok": true,
      "url": "https://satys.ift.org.mx/Sarccontroller#",
      "fuente": "DOCUMENTOS_ANEXOS"
    },
    {
      "folio": "178112",
      "archivo": "Sarccontroller_2",
      "nombre_original": "documento_178112_12",
      "tipo": "",
      "fecha": "",
      "descripcion": "",
      "ruta": "descargas\\178112\\Sarccontroller_2",
      "tamano_kb": 26.6,
      "ok": true,
      "url": "https://satys.ift.org.mx/Sarccontroller#",
      "fuente": "DOCUMENTOS_ANEXOS"
    }
  ]
}